experiment_results_manager/__init__.py
experiment_results_manager/artifact.py
experiment_results_manager/compare_runs.py
experiment_results_manager/experiment_run.py
experiment_results_manager/fsspec_util.py
experiment_results_manager/html_util.py
experiment_results_manager/registry.py
experiment_results_manager/serde.py
experiment_results_manager-0.1.2.dist-info/LICENSE
experiment_results_manager-0.1.2.dist-info/WHEEL
experiment_results_manager-0.1.2.dist-info/METADATA
experiment_results_manager-0.1.2.dist-info/RECORD
