Metadata-Version: 2.1
Name: experiment-results-manager
Version: 0.1.2
Summary: Light-weight experiment tracker
Home-page: https://github.com/ml-cyclops/experiment-results-manager
Author: sa-
Author-email: name@example.com
Requires-Python: >=3.8
Classifier: Programming Language :: Python :: 3
Classifier: Programming Language :: Python :: 3.10
Classifier: Programming Language :: Python :: 3.8
Classifier: Programming Language :: Python :: 3.9
Requires-Dist: fsspec (>=2021.4)
Requires-Dist: pydantic (>=1.6,<2.0)
Project-URL: Documentation, https://github.com/ml-cyclops/experiment-results-manager/blob/main/README.md
Project-URL: Repository, https://github.com/ml-cyclops/experiment-results-manager
